mcp_server_weibo/README.md
mcp_server_weibo/__init__.py
mcp_server_weibo/consts.py
mcp_server_weibo/schemas.py
mcp_server_weibo/server.py
mcp_server_weibo/weibo.py
mcp_server_weibo-1.0.7.dist-info/METADATA
mcp_server_weibo-1.0.7.dist-info/WHEEL
mcp_server_weibo-1.0.7.dist-info/entry_points.txt
mcp_server_weibo-1.0.7.dist-info/licenses/LICENSE
mcp_server_weibo-1.0.7.dist-info/RECORD
